trbnet/__init__.py
trbnet/core/__init__.py
trbnet/core/error.py
trbnet/core/highlevel.py
trbnet/core/libutils.py
trbnet/core/lowlevel.py
trbnet/epics/__init__.py
trbnet/epics/helpers.py
trbnet/epics/pcaspy_ioc.py
trbnet/util/trbcmd.py
trbnet/xmldb/__init__.py
trbnet/xmldb/db.py
trbnet-1.0.6.dist-info/METADATA
trbnet-1.0.6.dist-info/WHEEL
trbnet-1.0.6.dist-info/entry_points.txt
trbnet-1.0.6.dist-info/top_level.txt
trbnet-1.0.6.dist-info/zip-safe
trbnet-1.0.6.dist-info/RECORD
