Metadata-Version: 2.1
Name: trbnet
Version: 1.0.6
Summary: Interface to TrbNet (wrapping libtrbnet.so with ctypes)
Home-page: https://github.com/pklaus/pytrbnet
Author: Philipp Klaus
Author-email: klaus@physik.uni-frankfurt.de
License: GPL
Keywords: TrbNet,PyTrbNet,FPGA,low-latency,network,libtrbnet,wrapper
Platform: Linux
Classifier: Development Status :: 4 - Beta
Classifier: Operating System :: OS Independent
Classifier: License :: OSI Approved :: GNU General Public License v3 or later (GPLv3+)
Classifier: Programming Language :: Python
Classifier: Programming Language :: Python :: 3
Classifier: Topic :: Scientific/Engineering :: Physics
Classifier: Topic :: Scientific/Engineering :: Interface Engine/Protocol Translator
Classifier: Topic :: System :: Hardware :: Hardware Drivers
Requires-Dist: lxml
Requires-Dist: click
Requires-Dist: enum34 ; python_version < "3.4"
Requires-Dist: typing ; python_version < "3.5"
Provides-Extra: epics
Requires-Dist: pcaspy ; extra == 'epics'
